LICENSE
MANIFEST.in
README.rst
setup.cfg
setup.py
simrel/__init__.py
simrel/simrel.py
simrel/utilities.py
simrel/version.py
simrel.egg-info/PKG-INFO
simrel.egg-info/SOURCES.txt
simrel.egg-info/dependency_links.txt
simrel.egg-info/requires.txt
simrel.egg-info/top_level.txt