Metadata-Version: 1.1
Name: simrel
Version: 0.5.52
Summary: Simulation of linear model data
Home-page: https://github.com/simulatr/simrely
Author: Raju Rimal
Author-email: raju.rimal@nmbu.no
License: UNKNOWN
Keywords: multivariate simulation simrel linear-model
Platform: UNKNOWN
Classifier: Development Status :: 3 - Alpha
Classifier: License :: OSI Approved :: MIT License
Classifier: Programming Language :: Python :: 2
Classifier: Programming Language :: Python :: 2.7
Classifier: Programming Language :: Python :: 3
Classifier: Programming Language :: Python :: 3.4
Classifier: Programming Language :: Python :: 3.5
Classifier: Programming Language :: Python :: 3.6
